romiee/__init__.py
romiee/cli.py
romiee/scraper.py
romiee-0.1.0.dist-info/licenses/LICENSE
romiee-0.1.0.dist-info/METADATA
romiee-0.1.0.dist-info/WHEEL
romiee-0.1.0.dist-info/entry_points.txt
romiee-0.1.0.dist-info/top_level.txt
romiee-0.1.0.dist-info/RECORD
