Metadata-Version: 2.4
Name: romiee
Version: 0.1.0
Summary: A beginner-friendly web scraping kit
Home-page: https://github.com/yourusername/romiee
Author: Ramsha Noshad
Author-email: your@email.com
Classifier: Programming Language :: Python :: 3
Classifier: License :: OSI Approved :: MIT License
Requires-Python: >=3.6
License-File: LICENSE
Requires-Dist: requests
Requires-Dist: beautifulsoup4
Dynamic: author
Dynamic: author-email
Dynamic: classifier
Dynamic: description
Dynamic: description-content-type
Dynamic: home-page
Dynamic: license-file
Dynamic: requires-dist
Dynamic: requires-python
Dynamic: summary
